linna
