Metadata-Version: 2.1
Name: linna
Version: 0.0.2
Summary: Likelihood inference with neural network acceleration
Home-page: https://github.com/chto/linna
Author: Chun-Hao To
Author-email: chunhaoto@gmail.com
License: MIT license
Keywords: linna
Platform: UNKNOWN
Classifier: Development Status :: 2 - Pre-Alpha
Classifier: Intended Audience :: Developers
Classifier: License :: OSI Approved :: MIT License
Classifier: Natural Language :: English
Classifier: Programming Language :: Python :: 3
Classifier: Programming Language :: Python :: 3.6
Classifier: Programming Language :: Python :: 3.7
Classifier: Programming Language :: Python :: 3.8
Requires-Python: >=3.6
License-File: LICENSE
License-File: AUTHORS.rst
